synchronaut/__init__.py
synchronaut/core.py
synchronaut/synchronaut.py
synchronaut/utils.py
synchronaut-0.3.5.dist-info/METADATA
synchronaut-0.3.5.dist-info/WHEEL
synchronaut-0.3.5.dist-info/entry_points.txt
synchronaut-0.3.5.dist-info/licenses/LICENSE
synchronaut-0.3.5.dist-info/RECORD
