Metadata-Version: 2.4
Name: synchronaut
Version: 0.3.5
Summary: A “write-once, run‐anywhere” sync/async bridge that’s thread-safe, decorator-driven, and plays nicely in FastAPI (or other frameworks) & with DB connections.
Project-URL: Homepage, https://github.com/cachetronaut/synchronaut
Project-URL: Issues, https://github.com/cachetronaut/synchronaut/issues
Project-URL: Documentation, https://github.com/cachetronaut/synchronaut
Project-URL: Repository, https://github.com/cachetronaut/synchronaut
Author-email: cachetronaut <abrahamacastro+code@gmail.com>
License-File: LICENSE
Keywords: ContextVar,anyio,api,async,asynchronous,asyncio,call_any,call_map,cancellation,concurrency,concurrent,context-propagation,context-vars,contextvar,database,db,decorator,decorators,event-loop,executor,fastapi,fastio,hybrid-sync-async,interop,interop-library,io-bound,library,offload,offloading,package,pydantic,python,request-context,spawn-thread-with-ctx,structured-concurrency,sync,synchronaut,synchronous,task-scheduling,thread,thread-pool,thread-safe,threading,timeout,timeouts,trio,utili
Classifier: Development Status :: 4 - Beta
Classifier: Environment :: Web Environment
Classifier: Framework :: AnyIO
Classifier: Framework :: AsyncIO
Classifier: Framework :: FastAPI
Classifier: Framework :: Pytest
Classifier: Framework :: Trio
Classifier: Intended Audience :: Developers
Classifier: License :: OSI Approved :: MIT License
Classifier: Natural Language :: English
Classifier: Operating System :: OS Independent
Classifier: Programming Language :: Python
Classifier: Programming Language :: Python :: 3
Classifier: Programming Language :: Python :: 3.10
Classifier: Programming Language :: Python :: 3.11
Classifier: Programming Language :: Python :: 3.12
Classifier: Programming Language :: Python :: 3.13
Classifier: Topic :: Internet
Classifier: Topic :: Software Development :: Libraries :: Python Modules
Classifier: Topic :: Software Development :: Testing
Classifier: Typing :: Typed
Requires-Python: >=3.10
Requires-Dist: anyio>=4.9.0
Requires-Dist: asyncio>=3.4.3
Requires-Dist: trio>=0.30.0
Provides-Extra: fast
Requires-Dist: uvloop>=0.21.0; extra == 'fast'
